rki_covid19csv_parser/__init__.py
rki_covid19csv_parser/csv_parser.py
rki_covid19csv_parser/data/Bundesland_id.csv
rki_covid19csv_parser/data/Landkreis_id.csv
rki_covid19csv_parser/data/SOURCES.txt
rki_covid19csv_parser-1.2.0.dist-info/LICENSE
rki_covid19csv_parser-1.2.0.dist-info/METADATA
rki_covid19csv_parser-1.2.0.dist-info/WHEEL
rki_covid19csv_parser-1.2.0.dist-info/top_level.txt
rki_covid19csv_parser-1.2.0.dist-info/RECORD
