Metadata-Version: 2.1
Name: rki-covid19csv-parser
Version: 1.2.0
Summary: A simple module to work with the RKI_COVID19.csv files issued by the Robert-Koch-Institut in Germany.
Home-page: https://github.com/Hoffmann77/rki-covid19csv-cases
Author: Julius Hoffmann
Author-email: julius.Ho@web.de
License: UNKNOWN
Project-URL: Bug Tracker, https://github.com/Hoffmann77/rki-covid19csv-cases/issues
Project-URL: Changelog, https://github.com/Hoffmann77/rki-covid19csv-parser/blob/main/CHANGELOG.md
Platform: UNKNOWN
Classifier: Programming Language :: Python :: 3
Classifier: License :: OSI Approved :: MIT License
Classifier: Operating System :: OS Independent
Classifier: Development Status :: 5 - Production/Stable
Requires-Python: >=3.6
Requires-Dist: numpy
Requires-Dist: python-dateutil
